amba apb/amba_apb.v
`timescale 1ns/1ns



module APB_Protocol(
                 input PCLK,PRESETn,transfer,READ_WRITE,
                 input [8:0] apb_write_paddr,
		 input [7:0]apb_write_data,
		 input [8:0] apb_read_paddr,
		 output PSLVERR, 
                 output [7:0] apb_read_data_out
          );

       wire [7:0]PWDATA,PRDATA,PRDATA1,PRDATA2;
       wire [8:0]PADDR;

       wire PREADY,PREADY1,PREADY2,PENABLE,PSEL1,PSEL2,PWRITE;
    
    assign PREADY = PADDR[8] ? PREADY2 : PREADY1 ;
        assign PRDATA = READ_WRITE ? (PADDR[8] ? PRDATA2 : PRDATA1) : 8'dx ;

       master_bridge dut_mas(
	             apb_write_paddr,
		     apb_read_paddr,
		     apb_write_data,
		     PRDATA,         
	             PRESETn,
		     PCLK,
		     READ_WRITE,
		     transfer,
		     PREADY,
	             PSEL1,
		     PSEL2,
		     PENABLE,
	             PADDR,
	             PWRITE,
	             PWDATA,
		     apb_read_data_out,
		     PSLVERR
	               ); 


      slave1 dut1(  PCLK,PRESETn, PSEL1,PENABLE,PWRITE, PADDR[7:0],PWDATA, PRDATA1, PREADY1 );

   
endmodule

module master_bridge(
	input [8:0]apb_write_paddr,apb_read_paddr,
	input [7:0] apb_write_data,PRDATA,         
	input PRESETn,PCLK,READ_WRITE,transfer,PREADY,
	output PSEL1,PSEL2,
	output reg PENABLE,
	output reg [8:0]PADDR,
	output reg PWRITE,
	output reg [7:0]PWDATA,apb_read_data_out,
	output PSLVERR ); 
   
  reg [2:0] state, next_state;

  reg invalid_setup_error,
      setup_error,
      invalid_read_paddr,
      invalid_write_paddr,
      invalid_write_data ;
  
  localparam IDLE = 3'b001, SETUP = 3'b010, ENABLE = 3'b100 ;


  always @(posedge PCLK)
  begin
	if(!PRESETn)
		state <= IDLE;
	else
		state <= next_state; 
  end

  always @(state,transfer,PREADY)

  begin
	if(!PRESETn)
	  next_state = IDLE;
	else
          begin
             PWRITE = ~READ_WRITE;
	     case(state)
                  
		     IDLE: begin 
		              PENABLE =0;

		            if(!transfer)
	        	      next_state = IDLE ;
	                    else
			      next_state = SETUP;
	                   end

	       	SETUP:   begin
			    PENABLE =0;

			    if(READ_WRITE) 
	                       begin   PADDR = apb_read_paddr; end
			    else 
			      begin   
                                  PADDR = apb_write_paddr;
				  PWDATA = apb_write_data;  end
			    
			    if(transfer && !PSLVERR)
			      next_state = ENABLE;
		            else
           	              next_state = IDLE;
		           end

	       	ENABLE: 
		     begin if(PSEL1 || PSEL2)
		           PENABLE =1;
			   if(transfer & !PSLVERR)
			   begin
				   if(PREADY)
				   begin
					if(!READ_WRITE)
				         begin
				          
					   next_state = SETUP; end
					else 
					   begin
					   next_state = SETUP; 
				          	   
                apb_read_data_out = PRDATA; 
					   end
			            end
				    else next_state = ENABLE;
		              end
		             else next_state = IDLE;
			 end
           
           default: next_state = IDLE; 
               	endcase
             end
          end
  
  assign {PSEL1,PSEL2} = ((state != IDLE) ? (PADDR[8] ? {1'b0,1'b1} : {1'b1,1'b0}) : 2'd0);

  // PSLVERR LOGIC
  
  always @(*)
       begin
        if(!PRESETn)
	    begin 
	     setup_error =0;
	     invalid_read_paddr = 0;
	     invalid_write_paddr = 0;
	     invalid_write_paddr =0 ;
	    end
        else
	 begin	
          begin
	  if(state == IDLE && next_state == ENABLE)
   		  setup_error = 1;
	  else setup_error = 0;
          end
          begin
          if((apb_write_data===8'dx) && (!READ_WRITE) && (state==SETUP || state==ENABLE))
		  invalid_write_data =1;
	  else invalid_write_data = 0;
          end
          begin
	  if((apb_read_paddr===9'dx) && READ_WRITE && (state==SETUP || state==ENABLE))
		  invalid_read_paddr = 1;
	  else  invalid_read_paddr = 0;
          end
          begin
          if((apb_write_paddr===9'dx) && (!READ_WRITE) && (state==SETUP || state==ENABLE))
		  invalid_write_paddr =1;
          else invalid_write_paddr =0;
          end
          begin
	  if(state == SETUP)
            begin
                 if(PWRITE)
                      begin
                         if(PADDR==apb_write_paddr && PWDATA==apb_write_data)
                              setup_error=1'b0;
                         else
                               setup_error=1'b1;
                       end
                 else 
                       begin
                          if (PADDR==apb_read_paddr)
                                 setup_error=1'b0;
                          else
                                 setup_error=1'b1;
                       end    
              end 
          
         else setup_error=1'b0;
         end 
       end
       invalid_setup_error = setup_error ||  invalid_read_paddr || invalid_write_data || invalid_write_paddr  ;
     end 

   assign PSLVERR =  invalid_setup_error ;

	 

 endmodule

module slave1(
         input PCLK,PRESETn,
         input PSEL,PENABLE,PWRITE,
         input [7:0]PADDR,PWDATA,
        output [7:0]PRDATA1,
        output reg PREADY );
    
     reg [7:0]reg_addr;
     reg [7:0] mem [0:63];

    assign PRDATA1 =  mem[reg_addr];

    always @(*)
       begin
         if(!PRESETn)
              PREADY = 0;
          else
	  if(PSEL && !PENABLE && !PWRITE)
	     begin PREADY = 0; end
	         
	  else if(PSEL && PENABLE && !PWRITE)
	     begin  PREADY = 1;
                    reg_addr =  PADDR; 
	       end
          else if(PSEL && !PENABLE && PWRITE)
	     begin  PREADY = 0; end

	  else if(PSEL && PENABLE && PWRITE)
	     begin  PREADY = 1;
	            mem[PADDR] = PWDATA; end

           else PREADY = 0;
        end
    endmodule

amba apb/amba_apbtb.v
`timescale 1ns/1ns


  module test;
 
  reg PCLK,PRESETn,transfer,READ_WRITE;
  reg [8:0]apb_write_paddr;
  reg [7:0]apb_write_data;
  reg [8:0]apb_read_paddr;
  wire [7:0]apb_read_data_out;
  wire PSLVERR;
  reg [7:0]data,expected;

  reg [7:0]mem[0:15];
  
  APB_Protocol dut_c(  PCLK,
	               PRESETn,
		       transfer,
		       READ_WRITE,
                       apb_write_paddr,
		       apb_write_data,
		       apb_read_paddr,
		       PSLVERR, 
                       apb_read_data_out
	                 );
  integer i,j;
  initial
   begin
    PCLK <= 0;
    forever #5 PCLK = ~PCLK;
   end

    initial
    begin
                                    PRESETn<=0; transfer<=0; READ_WRITE =0;
               @(posedge PCLK)      PRESETn = 1;                                     //no write address available but request for write operation
               @(posedge PCLK)      transfer = 1;
     repeat(2) @(posedge PCLK);
               @(negedge PCLK)      Write_slave1;        // write operation

   //            @(posedge PCLK);    apb_write_paddr = 9'd526;  apb_write_data = 9'd9;
    // repeat(2) @(posedge PCLK);    apb_write_paddr = 9'd22; apb_write_data = 9'd35;
     repeat(2) @(posedge PCLK);
               @(posedge PCLK)     READ_WRITE =1; PRESETn<=0; transfer<=0; 
               @(posedge PCLK)     PRESETn = 1;
     repeat(3) @(posedge PCLK)     transfer = 1;                             // no read address available but request for read operation
     repeat(2) @(posedge PCLK)     Read_slave1;                             //read operation

     repeat(3) @(posedge PCLK);   apb_read_paddr = 9'd45;                 //data not inserted in write operation but requested for read operation
     repeat(4) @(posedge PCLK);
     $finish;
  end

    task Write_slave1;

     begin
 	transfer =1;
	for (i = 0; i < 8; i=i+1) begin
	repeat(2)@(negedge PCLK)
        begin    
             	data = i;
		apb_write_data = 2*i;
		apb_write_paddr =  {1'b0,data};
	//	mem[i] = (2*i);
                
	 end 
	end

     end
endtask

		 
  task Read_slave1;
     

      begin 
	for (j = 0;  j< 8; j= j+1)
        begin
	repeat(2)@(negedge PCLK)
          begin  
	  data = j; 
	  apb_read_paddr = {1'b0,data};

         end
        end
      end
  endtask


    
  initial
   begin
    $dumpfile("apbWaveform.vcd");
    $dumpvars;
   end

 endmodule

amba apb/apbWaveform.vcd
$date
	Wed Feb  8 15:11:29 2023
$end
$version
	Icarus Verilog
$end
$timescale
	1ns
$end
$scope module test $end
$var wire 8 ! apb_read_data_out [7:0] $end
$var wire 1 " PSLVERR $end
$var reg 1 # PCLK $end
$var reg 1 $ PRESETn $end
$var reg 1 % READ_WRITE $end
$var reg 9 & apb_read_paddr [8:0] $end
$var reg 8 ' apb_write_data [7:0] $end
$var reg 9 ( apb_write_paddr [8:0] $end
$var reg 8 ) data [7:0] $end
$var reg 1 * transfer $end
$var integer 32 + i [31:0] $end
$var integer 32 , j [31:0] $end
$scope module dut_c $end
$var wire 1 # PCLK $end
$var wire 8 - PRDATA2 [7:0] $end
$var wire 1 . PREADY2 $end
$var wire 1 $ PRESETn $end
$var wire 1 % READ_WRITE $end
$var wire 9 / apb_read_paddr [8:0] $end
$var wire 8 0 apb_write_data [7:0] $end
$var wire 9 1 apb_write_paddr [8:0] $end
$var wire 1 * transfer $end
$var wire 8 2 apb_read_data_out [7:0] $end
$var wire 1 3 PWRITE $end
$var wire 8 4 PWDATA [7:0] $end
$var wire 1 " PSLVERR $end
$var wire 1 5 PSEL2 $end
$var wire 1 6 PSEL1 $end
$var wire 1 7 PREADY1 $end
$var wire 1 8 PREADY $end
$var wire 8 9 PRDATA1 [7:0] $end
$var wire 8 : PRDATA [7:0] $end
$var wire 1 ; PENABLE $end
$var wire 9 < PADDR [8:0] $end
$scope module dut1 $end
$var wire 8 = PADDR [7:0] $end
$var wire 1 # PCLK $end
$var wire 8 > PRDATA1 [7:0] $end
$var wire 1 $ PRESETn $end
$var wire 1 3 PWRITE $end
$var wire 8 ? PWDATA [7:0] $end
$var wire 1 6 PSEL $end
$var wire 1 ; PENABLE $end
$var reg 1 7 PREADY $end
$var reg 8 @ reg_addr [7:0] $end
$upscope $end
$scope module dut_mas $end
$var wire 1 # PCLK $end
$var wire 8 A PRDATA [7:0] $end
$var wire 1 8 PREADY $end
$var wire 1 $ PRESETn $end
$var wire 1 " PSLVERR $end
$var wire 1 % READ_WRITE $end
$var wire 9 B apb_read_paddr [8:0] $end
$var wire 8 C apb_write_data [7:0] $end
$var wire 9 D apb_write_paddr [8:0] $end
$var wire 1 * transfer $end
$var wire 1 5 PSEL2 $end
$var wire 1 6 PSEL1 $end
$var reg 9 E PADDR [8:0] $end
$var reg 1 ; PENABLE $end
$var reg 8 F PWDATA [7:0] $end
$var reg 1 3 PWRITE $end
$var reg 8 G apb_read_data_out [7:0] $end
$var reg 1 H invalid_read_paddr $end
$var reg 1 I invalid_setup_error $end
$var reg 1 J invalid_write_data $end
$var reg 1 K invalid_write_paddr $end
$var reg 3 L next_state [2:0] $end
$var reg 1 M setup_error $end
$var reg 3 N state [2:0] $end
$upscope $end
$upscope $end
$scope task Read_slave1 $end
$upscope $end
$scope task Write_slave1 $end
$upscope $end
$upscope $end
$enddefinitions $end
#0
$dumpvars
bx N
0M
b1 L
0K
0J
0I
0H
bx G
bx F
bx E
bx D
bx C
bx B
bx A
bx @
bx ?
bx >
bx =
bx <
x;
bx :
bx 9
x8
07
x6
x5
bx 4
x3
bx 2
bx 1
bx 0
bx /
z.
bz -
bx ,
bx +
0*
bx )
bx (
bx '
bx &
0%
0$
0#
0"
bx !
$end
#5
05
06
0;
13
b1 N
1$
1#
#10
0#
#15
b10 L
1*
1#
#20
0#
#25
x5
x6
1"
1I
1M
1K
1J
b100 L
b10 N
1#
#30
0#
#35
0M
b1 L
b100 N
1#
#40
b0 +
0#
#45
05
06
0"
0I
0K
0J
b10 L
b1 N
1#
#50
b0 (
b0 1
b0 D
b0 '
b0 0
b0 C
b0 )
0#
#55
08
b0 =
05
16
b100 L
b0 4
b0 ?
b0 F
b0 <
b0 E
b10 N
1#
#60
b1 +
0#
#65
b10 L
18
17
1;
b100 N
1#
#70
b1 (
b1 1
b1 D
b10 '
b10 0
b10 C
b1 )
0#
#75
08
b1 =
07
b100 L
b10 4
b10 ?
b10 F
b1 <
b1 E
0;
b10 N
1#
#80
b10 +
0#
#85
b10 L
18
17
1;
b100 N
1#
#90
b10 (
b10 1
b10 D
b100 '
b100 0
b100 C
b10 )
0#
#95
08
b10 =
07
b100 L
b100 4
b100 ?
b100 F
b10 <
b10 E
0;
b10 N
1#
#100
b11 +
0#
#105
b10 L
18
17
1;
b100 N
1#
#110
b11 (
b11 1
b11 D
b110 '
b110 0
b110 C
b11 )
0#
#115
08
b11 =
07
b100 L
b110 4
b110 ?
b110 F
b11 <
b11 E
0;
b10 N
1#
#120
b100 +
0#
#125
b10 L
18
17
1;
b100 N
1#
#130
b100 (
b100 1
b100 D
b1000 '
b1000 0
b1000 C
b100 )
0#
#135
08
b100 =
07
b100 L
b1000 4
b1000 ?
b1000 F
b100 <
b100 E
0;
b10 N
1#
#140
b101 +
0#
#145
b10 L
18
17
1;
b100 N
1#
#150
b101 (
b101 1
b101 D
b1010 '
b1010 0
b1010 C
b101 )
0#
#155
08
b101 =
07
b100 L
b1010 4
b1010 ?
b1010 F
b101 <
b101 E
0;
b10 N
1#
#160
b110 +
0#
#165
b10 L
18
17
1;
b100 N
1#
#170
b110 (
b110 1
b110 D
b1100 '
b1100 0
b1100 C
b110 )
0#
#175
08
b110 =
07
b100 L
b1100 4
b1100 ?
b1100 F
b110 <
b110 E
0;
b10 N
1#
#180
b111 +
0#
#185
b10 L
18
17
1;
b100 N
1#
#190
b111 (
b111 1
b111 D
b1110 '
b1110 0
b1110 C
b111 )
0#
#195
08
b111 =
07
b100 L
b1110 4
b1110 ?
b1110 F
b111 <
b111 E
0;
b10 N
1#
#200
b1000 +
0#
#205
b10 L
18
17
1;
b100 N
1#
#210
0#
#215
08
07
b100 L
0;
b10 N
1#
#220
0#
#225
b1 L
b100 N
0*
0$
0"
0I
0H
1%
1#
#230
0#
#235
06
03
b1 N
0"
0I
0H
1$
1#
#240
0#
#245
b10 L
1*
1#
#250
0#
#255
x5
x8
bx =
x6
1"
1I
1M
1H
b1 L
bx <
bx E
b10 N
1#
#260
0#
#265
05
06
0"
0I
0H
0M
b10 L
b1 N
1#
#270
0#
#275
x5
x6
1"
1I
1M
1H
b100 L
b10 N
b0 ,
1#
#280
0H
1M
b0 &
b0 /
b0 B
b0 )
0#
#285
0"
0I
0M
b1 L
b100 N
1#
#290
b1 ,
0#
#295
05
06
b10 L
b1 N
1#
#300
b1 &
b1 /
b1 B
b1 )
0#
#305
08
b1 =
05
16
b100 L
b1 <
b1 E
b10 N
1#
#310
b10 ,
0#
#315
b10 :
b10 A
b10 L
18
b10 9
b10 >
b1 @
17
1;
b100 N
1#
#320
b10 &
b10 /
b10 B
b10 )
0#
#325
08
b10 =
07
b100 L
b10 <
b10 E
0;
b10 N
1#
#330
b11 ,
0#
#335
b100 :
b100 A
b10 !
b10 2
b10 G
b10 L
18
b100 9
b100 >
b10 @
17
1;
b100 N
1#
#340
b11 &
b11 /
b11 B
b11 )
0#
#345
08
b11 =
07
b100 L
b11 <
b11 E
0;
b10 N
1#
#350
b100 ,
0#
#355
b110 :
b110 A
b100 !
b100 2
b100 G
b10 L
18
b110 9
b110 >
b11 @
17
1;
b100 N
1#
#360
b100 &
b100 /
b100 B
b100 )
0#
#365
08
b100 =
07
b100 L
b100 <
b100 E
0;
b10 N
1#
#370
b101 ,
0#
#375
b1000 :
b1000 A
b110 !
b110 2
b110 G
b10 L
18
b1000 9
b1000 >
b100 @
17
1;
b100 N
1#
#380
b101 &
b101 /
b101 B
b101 )
0#
#385
08
b101 =
07
b100 L
b101 <
b101 E
0;
b10 N
1#
#390
b110 ,
0#
#395
b1010 :
b1010 A
b1000 !
b1000 2
b1000 G
b10 L
18
b1010 9
b1010 >
b101 @
17
1;
b100 N
1#
#400
b110 &
b110 /
b110 B
b110 )
0#
#405
08
b110 =
07
b100 L
b110 <
b110 E
0;
b10 N
1#
#410
b111 ,
0#
#415
b1100 :
b1100 A
b1010 !
b1010 2
b1010 G
b10 L
18
b1100 9
b1100 >
b110 @
17
1;
b100 N
1#
#420
b111 &
b111 /
b111 B
b111 )
0#
#425
08
b111 =
07
b100 L
b111 <
b111 E
0;
b10 N
1#
#430
b1000 ,
0#
#435
b1110 :
b1110 A
b1100 !
b1100 2
b1100 G
b10 L
18
b1110 9
b1110 >
b111 @
17
1;
b100 N
b0 ,
1#
#440
b0 &
b0 /
b0 B
b0 )
0#
#445
08
b0 =
07
b100 L
b0 <
b0 E
0;
b10 N
1#
#450
b1 ,
0#
#455
b0 :
b0 A
b1110 !
b1110 2
b1110 G
b10 L
18
b0 9
b0 >
b0 @
17
1;
b100 N
1#
#460
b1 &
b1 /
b1 B
b1 )
0#
#465
08
b1 =
07
b100 L
b1 <
b1 E
0;
b10 N
1#
#470
b10 ,
0#
#475
b10 :
b10 A
b0 !
b0 2
b0 G
b10 L
18
b10 9
b10 >
b1 @
17
1;
b100 N
1#
#480
b10 &
b10 /
b10 B
b10 )
0#
#485
08
b10 =
07
b100 L
b10 <
b10 E
0;
b10 N
1#
#490
b11 ,
0#
#495
b100 :
b100 A
b10 !
b10 2
b10 G
b10 L
18
b100 9
b100 >
b10 @
17
1;
b100 N
1#
#500
b11 &
b11 /
b11 B
b11 )
0#
#505
08
b11 =
07
b100 L
b11 <
b11 E
0;
b10 N
1#
#510
b100 ,
0#
#515
b110 :
b110 A
b100 !
b100 2
b100 G
b10 L
18
b110 9
b110 >
b11 @
17
1;
b100 N
1#
#520
b100 &
b100 /
b100 B
b100 )
0#
#525
08
b100 =
07
b100 L
b100 <
b100 E
0;
b10 N
1#
#530
b101 ,
0#
#535
b1000 :
b1000 A
b110 !
b110 2
b110 G
b10 L
18
b1000 9
b1000 >
b100 @
17
1;
b100 N
1#
#540
b101 &
b101 /
b101 B
b101 )
0#
#545
08
b101 =
07
b100 L
b101 <
b101 E
0;
b10 N
1#
#550
b110 ,
0#
#555
b1010 :
b1010 A
b1000 !
b1000 2
b1000 G
b10 L
18
b1010 9
b1010 >
b101 @
17
1;
b100 N
1#
#560
b110 &
b110 /
b110 B
b110 )
0#
#565
08
b110 =
07
b100 L
b110 <
b110 E
0;
b10 N
1#
#570
b111 ,
0#
#575
b1100 :
b1100 A
b1010 !
b1010 2
b1010 G
b10 L
18
b1100 9
b1100 >
b110 @
17
1;
b100 N
1#
#580
b111 &
b111 /
b111 B
b111 )
0#
#585
08
b111 =
07
b100 L
b111 <
b111 E
0;
b10 N
1#
#590
b1000 ,
0#
#595
b1110 :
b1110 A
b1100 !
b1100 2
b1100 G
b10 L
18
b1110 9
b1110 >
b111 @
17
1;
b100 N
1#
#600
0#
#605
08
07
b100 L
0;
b10 N
1#
#610
0#
#615
b1110 !
b1110 2
b1110 G
18
17
b10 L
1;
b100 N
0"
0I
0M
b101101 &
b101101 /
b101101 B
1#
#620
0#
#625
08
b101101 =
07
b100 L
b101101 <
b101101 E
0;
b10 N
1#
#630
0#
#635
bx :
bx A
b10 L
18
bx 9
bx >
b101101 @
17
1;
b100 N
1#
#640
0#
#645
08
07
b100 L
0;
b10 N
1#
#650
0#
#655
bx !
bx 2
bx G
b10 L
18
17
1;
b100 N
1#
